[
  {
    "value": "toolkit_pb_magia_y_divinidad",
    "name": "PB - Toolkit Magia y Divinidad"
  },
  {
    "value": "toolkit_pb_fuerza_y_destino",
    "name": "PB - Toolkit Fuerza y Destino"
  },
  {
    "value": "leyendas_pb_3.0",
    "name": "PB - Leyendas 3.0"
  },
  {
    "value": "pb_lootbox_2023",
    "name": "PB - LootBox 2023"
  },
  {
    "value": "dracula_pb",
    "name": "PB - Drácula"
  },
  {
    "value": "shogun_ii",
    "name": "PB - Shogun II"
  },
  {
    "value": "helenica_aniversario",
    "name": "PB - Helénica Aniversario"
  },
  {
    "value": "colecciones_raciales_pb_2023",
    "name": "PB - Colecciones Raciales Pb 2023"
  },
  {
    "value": "relatos_espada_sagrada_aniversario",
    "name": "PB - Relatos Espada Sagrada Aniversario"
  },
  {
    "value": "espada_sagrada_aniversario",
    "name": "PB - Espada Sagrada Aniversario"
  },
  {
    "value": "extensiones_pb_2023",
    "name": "PB - Extensiones Primer Bloque 2023"
  },
  {
    "value": "toolkit_fe_sin_limite",
    "name": "PB - Toolkit Fe sin Limite"
  },
  {
    "value": "toolkit_dragon_dorado",
    "name": "PB - Toolkit Dragón Dorado"
  },
  {
    "value": "primer_bloque_2",
    "name": "PB - Leyendas 2.0"
  },
  {
    "value": "shogun_1",
    "name": "PB - Shogun"
  },
  {
    "value": "raciales_pb",
    "name": "PB - Raciales"
  },
  {
    "value": "promocionales_primer_bloque",
    "name": "PB - Promocionales PB"
  },
  {
    "value": "leyendas_primer_bloque",
    "name": "PB - Leyendas PB"
  },
  {
    "value": "encrucijada",
    "name": "PB - Encrucijada"
  },
  {
    "value": "dominios-de-ra",
    "name": "PB - Dominios de Ra"
  },
  {
    "value": "tierras_altas",
    "name": "PB - Tierras Altas"
  },
  {
    "value": "hijos_de_daana",
    "name": "PB - Hijos de Daana"
  },
  {
    "value": "imperio",
    "name": "PB - Imperio"
  },
  {
    "value": "helenica",
    "name": "PB - Helénica"
  },
  {
    "value": "cruzadas",
    "name": "PB - Cruzadas"
  },
  {
    "value": "espada-sagrada",
    "name": "PB - Espada Sagrada"
  }
]